wknml/__init__.py
wknml/nml_generation.py
wknml/nml_utils.py
wknml-1.1.3.dist-info/LICENSE
wknml-1.1.3.dist-info/METADATA
wknml-1.1.3.dist-info/WHEEL
wknml-1.1.3.dist-info/RECORD
