Metadata-Version: 2.1
Name: wknml
Version: 1.1.3
Summary: Python package to work with webKnossos NML skeleton files
Home-page: https://github.com/scalableminds/wknml
License: MIT
Author: scalable minds
Author-email: hello@scalableminds.com
Requires-Python: >=3.8,<4.0
Classifier: License :: OSI Approved :: MIT License
Classifier: Programming Language :: Python :: 3
Classifier: Programming Language :: Python :: 3.8
Classifier: Programming Language :: Python :: 3.9
Classifier: Programming Language :: Python :: 3.10
Classifier: Programming Language :: Python :: 3.11
Classifier: Programming Language :: Python :: 3.12
Requires-Dist: loxun (>=2.0,<3.0)
Requires-Dist: networkx (>=3,<4)
Requires-Dist: numpy (>=1.17.4)
Project-URL: Repository, https://github.com/scalableminds/wknml
